pyloco_task_docx2text/__init__.py
pyloco_task_docx2text/docx2text.py
pyloco_task_docx2text-0.1.2.dist-info/METADATA
pyloco_task_docx2text-0.1.2.dist-info/WHEEL
pyloco_task_docx2text-0.1.2.dist-info/entry_points.txt
pyloco_task_docx2text-0.1.2.dist-info/top_level.txt
pyloco_task_docx2text-0.1.2.dist-info/RECORD
