Metadata-Version: 2.1
Name: pyloco-task-docx2text
Version: 0.1.2
Summary: UNKNOWN
Home-page: UNKNOWN
Author: UNKNOWN
Author-email: UNKNOWN
License: UNKNOWN
Platform: UNKNOWN
Requires-Dist: python-docx (>=0.8.10)
Requires-Dist: pyloco (>=0.0.90)
